LICENSE
README.md
setup.cfg
setup.py
robobag/__init__.py
robobag/bag.py
robobag/cli.py
robobag/message.py
robobag/profile_pb2.py
robobag/util.py
robobag.egg-info/PKG-INFO
robobag.egg-info/SOURCES.txt
robobag.egg-info/dependency_links.txt
robobag.egg-info/entry_points.txt
robobag.egg-info/requires.txt
robobag.egg-info/top_level.txt