Metadata-Version: 1.0
Name: robobag
Version: 0.3.3
Summary: Tool for processing ros bag file.
Home-page: https://github.com/wzy816/bag
Author: UNKNOWN
Author-email: no-reply@gmail.com
License: Apache 2.0
Keywords: ros ,bag
Platform: UNKNOWN
